[
  {
    "id": "437",
    "subject": "“intern in the past 48h”: Nexxiot - IoT data simulation  internship posted on 6/8/26",
    "from": "LinkedIn Job Alerts <jobalerts-noreply@linkedin.com>",
    "date": "Tue, 9 Jun 2026 11:57:10 +0000 (UTC)",
    "snippet": "Your job alert for intern in the past 48h in Zurich          \r 30+ new jobs match your preferences.\r \r Results from the new AI-powered job search\r \r           \r IoT data simulation  internship\r Nexxio"
  },
  {
    "id": "430",
    "subject": "7 new job ads for your search alert: internship in Zurich",
    "from": "XING Jobs <jobs@mail.xing.com>",
    "date": "Tue, 9 Jun 2026 06:32:54 +0000",
    "snippet": "View message in browser: https://www.xing.com/m/vdw5wnO9N7XPeBAuAfBZgA\r \r \r XING\r \r ~~~~~~~~~~~~~~~~~~~~~~~~~~~~~~~~~~~~~~~~\r \r Hi Carlos,\r Check out what our AI-enhanced search found for you\r \r ~~~~~"
  },
  {
    "id": "432",
    "subject": "“internship or intern in the past…”: Nexxiot - IoT data simulation  internship posted on 6/8/26",
    "from": "LinkedIn Job Alerts <jobalerts-noreply@linkedin.com>",
    "date": "Tue, 9 Jun 2026 07:57:12 +0000 (UTC)",
    "snippet": "Your job alert for internship or intern in the past 48h in Zurich          \r 30+ new jobs match your preferences.\r \r Results from the new AI-powered job search\r \r           \r IoT data simulation  inte"
  },
  {
    "id": "431",
    "subject": "8 new job ads for your search alert: intern in Zurich",
    "from": "XING Jobs <jobs@mail.xing.com>",
    "date": "Tue, 9 Jun 2026 06:33:00 +0000",
    "snippet": "View message in browser: https://www.xing.com/m/ruLarlB1xl_4rUH_l1yogA\r \r \r XING\r \r ~~~~~~~~~~~~~~~~~~~~~~~~~~~~~~~~~~~~~~~~\r \r Hi Carlos,\r Check out what our AI-enhanced search found for you\r \r ~~~~~"
  },
  {
    "id": "434",
    "subject": "“internship in the past 48h”: Nexxiot - IoT data simulation  internship posted on 6/8/26",
    "from": "LinkedIn Job Alerts <jobalerts-noreply@linkedin.com>",
    "date": "Tue, 9 Jun 2026 09:57:09 +0000 (UTC)",
    "snippet": "Your job alert for internship in the past 48h in Zurich          \r 30+ new jobs match your preferences.\r \r Results from the new AI-powered job search\r \r           \r IoT data simulation  internship\r Ne"
  },
  {
    "id": "439",
    "subject": "SCALEUP.agency is hiring a AI & Business Analyst / Consultant\r\n (Remote Internship)",
    "from": "LinkedIn <jobs-listings@linkedin.com>",
    "date": "Tue, 9 Jun 2026 13:57:14 +0000 (UTC)",
    "snippet": "Top job picks for you:     https://www.linkedin.com/comm/jobs/collections/recommended?origin=JYMBII_EMAIL&lgCta=eml-jymbii-bottom-see-all-jobs&lgTemp=jobs_jymbii_digest&lipi=urn%3Ali%3Apage%3Aemail_jo"
  },
  {
    "id": "428",
    "subject": "1 new job offer found",
    "from": "\"jobup.ch Job Alert\" <noreply@jobup.ch>",
    "date": "Tue, 9 Jun 2026 04:59:01 +0000",
    "snippet": "New jobs for intern | internship Jobs\r \r \r ----------------------------------------\r >>Unsubscribe<<\r >>https://www.jobup.ch/en/account/job-alert/4ad6112e-996b-4776-a52f-e6a2c5d25506/?reference-date"
  },
  {
    "id": "438",
    "subject": "Hitachi Energy, Clayground.ai, ZURICH Versicherung Schweiz / ZURICH\r\n Group and other great companies are looking for candidates just like you!",
    "from": "XING Jobs <jobs@mail.xing.com>",
    "date": "Tue, 9 Jun 2026 13:54:22 +0000",
    "snippet": "View message in browser: https://www.xing.com/m/6oEqv_hJoNAxOrBzU0kVgA\r \r \r XING\r \r ~~~~~~~~~~~~~~~~~~~~~~~~~~~~~~~~~~~~~~~~\r \r Hi Carlos,\r We've got new job recommendations for you.\r \r ~~~~~~~~~~~~~~"
  }
]