[
  {
    "id": "510",
    "subject": "4 new job ads for your search alert: intern in Zurich",
    "from": "XING Jobs <jobs@mail.xing.com>",
    "date": "Sat, 13 Jun 2026 06:07:15 +0000",
    "snippet": "View message in browser: https://www.xing.com/m/bkZui5w361SWQUTEzWH2gA\r \r \r XING\r \r ~~~~~~~~~~~~~~~~~~~~~~~~~~~~~~~~~~~~~~~~\r \r Hi Carlos,\r Check out what our AI-enhanced search found for you\r \r ~~~~~"
  },
  {
    "id": "513",
    "subject": "“internship or intern in the past…”: Hitachi Energy - Internship in Low-Code Development 80 - 100% (f/m(d) posted on 6/12/26",
    "from": "LinkedIn Job Alerts <jobalerts-noreply@linkedin.com>",
    "date": "Sat, 13 Jun 2026 07:57:09 +0000 (UTC)",
    "snippet": "Your job alert for internship or intern in the past 48h in Zurich          \r 30+ new jobs match your preferences.\r Manage alerts: https://www.linkedin.com/comm/jobs/alerts?lipi=urn%3Ali%3Apage%3Aemail"
  },
  {
    "id": "511",
    "subject": "5 new job ads for your search alert: internship in Zurich",
    "from": "XING Jobs <jobs@mail.xing.com>",
    "date": "Sat, 13 Jun 2026 06:07:57 +0000",
    "snippet": "View message in browser: https://www.xing.com/m/kbFhOSzcc3owKyW-OpKTgA\r \r \r XING\r \r ~~~~~~~~~~~~~~~~~~~~~~~~~~~~~~~~~~~~~~~~\r \r Hi Carlos,\r Check out what our AI-enhanced search found for you\r \r ~~~~~"
  },
  {
    "id": "506",
    "subject": "Neue Jobs in  Zürich,  Schweiz. Bewirb dich noch heute!",
    "from": "Glassdoor-Jobs <noreply@glassdoor.com>",
    "date": "Fri, 12 Jun 2026 18:49:37 +0000 (UTC)",
    "snippet": "<!DOCTYPE html><html dir=\"ltr\" lang=\"en\"><head><link rel=\"preload\" as=\"image\" href=\"https://www.glassdoor.com/assets/email/brandRefresh/logo.png\"><link rel=\"preload\" as=\"image\" href=\"https://www.glass"
  },
  {
    "id": "512",
    "subject": "Project Support Intern 80-100% bei Lonza: Diese Stelle würde  zu dir passen",
    "from": "Glassdoor-Jobs <noreply@glassdoor.com>",
    "date": "Sat, 13 Jun 2026 07:05:12 +0000 (UTC)",
    "snippet": "<!DOCTYPE html PUBLIC \"-//W3C//DTD XHTML 1.0 Transitional//EN\" \"http://www.w3.org/TR/xhtml1/DTD/xhtml1-transitional.dtd\"><html dir=\"ltr\" lang=\"en\"><head><meta name=\"viewport\" content=\"width=device-wid"
  },
  {
    "id": "508",
    "subject": "3 new job offers found",
    "from": "\"jobup.ch Job Alert\" <noreply@jobup.ch>",
    "date": "Sat, 13 Jun 2026 04:58:02 +0000",
    "snippet": "New jobs for intern | internship Jobs\r \r \r ----------------------------------------\r >>Unsubscribe<<\r >>https://www.jobup.ch/en/account/job-alert/4ad6112e-996b-4776-a52f-e6a2c5d25506/?reference-date"
  }
]